MANIFEST.in
README
requirements.txt
setup.py
ajenti.plugin.notepad.egg-info/PKG-INFO
ajenti.plugin.notepad.egg-info/SOURCES.txt
ajenti.plugin.notepad.egg-info/dependency_links.txt
ajenti.plugin.notepad.egg-info/requires.txt
ajenti.plugin.notepad.egg-info/top_level.txt
ajenti_plugin_notepad/README.md
ajenti_plugin_notepad/__init__.py
ajenti_plugin_notepad/bower.json
ajenti_plugin_notepad/main.py
ajenti_plugin_notepad/plugin.yml
ajenti_plugin_notepad/requirements.txt
ajenti_plugin_notepad/locale/app.pot
ajenti_plugin_notepad/locale/af/LC_MESSAGES/app.js
ajenti_plugin_notepad/locale/af/LC_MESSAGES/app.po
ajenti_plugin_notepad/locale/ar/LC_MESSAGES/app.js
ajenti_plugin_notepad/locale/ar/LC_MESSAGES/app.po
ajenti_plugin_notepad/locale/be/LC_MESSAGES/app.js
ajenti_plugin_notepad/locale/be/LC_MESSAGES/app.po
ajenti_plugin_notepad/locale/bg/LC_MESSAGES/app.js
ajenti_plugin_notepad/locale/bg/LC_MESSAGES/app.po
ajenti_plugin_notepad/locale/bn/LC_MESSAGES/app.js
ajenti_plugin_notepad/locale/bn/LC_MESSAGES/app.po
ajenti_plugin_notepad/locale/bs/LC_MESSAGES/app.js
ajenti_plugin_notepad/locale/bs/LC_MESSAGES/app.po
ajenti_plugin_notepad/locale/ca/LC_MESSAGES/app.js
ajenti_plugin_notepad/locale/ca/LC_MESSAGES/app.po
ajenti_plugin_notepad/locale/cs/LC_MESSAGES/app.js
ajenti_plugin_notepad/locale/cs/LC_MESSAGES/app.po
ajenti_plugin_notepad/locale/da/LC_MESSAGES/app.js
ajenti_plugin_notepad/locale/da/LC_MESSAGES/app.po
ajenti_plugin_notepad/locale/de/LC_MESSAGES/app.js
ajenti_plugin_notepad/locale/de/LC_MESSAGES/app.po
ajenti_plugin_notepad/locale/el/LC_MESSAGES/app.js
ajenti_plugin_notepad/locale/el/LC_MESSAGES/app.po
ajenti_plugin_notepad/locale/en/LC_MESSAGES/app.po
ajenti_plugin_notepad/locale/eo/LC_MESSAGES/app.js
ajenti_plugin_notepad/locale/eo/LC_MESSAGES/app.po
ajenti_plugin_notepad/locale/es-ES/LC_MESSAGES/app.js
ajenti_plugin_notepad/locale/es-ES/LC_MESSAGES/app.po
ajenti_plugin_notepad/locale/et/LC_MESSAGES/app.js
ajenti_plugin_notepad/locale/et/LC_MESSAGES/app.po
ajenti_plugin_notepad/locale/fa/LC_MESSAGES/app.js
ajenti_plugin_notepad/locale/fa/LC_MESSAGES/app.po
ajenti_plugin_notepad/locale/fi/LC_MESSAGES/app.js
ajenti_plugin_notepad/locale/fi/LC_MESSAGES/app.po
