Metadata-Version: 1.2
Name: ajenti.plugin.notepad
Version: 0.30
Summary: Notepad
Home-page: https://ajenti.org
Author: Ajenti project
Author-email: e@ajenti.org
License: UNKNOWN
Platform: UNKNOWN
Requires-Python: >=3
